cubat/__init__.py
cubat/__main__.py
cubat/cli.py
cubat/core.py
cubat-0.1.5.dist-info/LICENSE
cubat-0.1.5.dist-info/METADATA
cubat-0.1.5.dist-info/WHEEL
cubat-0.1.5.dist-info/entry_points.txt
cubat-0.1.5.dist-info/top_level.txt
cubat-0.1.5.dist-info/RECORD
