Metadata-Version: 2.1
Name: cubat
Version: 0.1.5
Summary: CUBAT  -- CUB Analysis Toolkit
Home-page: https://gxelab.github.io/CUBAT/
License-File: LICENSE
Requires-Dist: click
Requires-Dist: numpy (~=1.21.1)
Requires-Dist: pandas (~=1.3.0)
Requires-Dist: statsmodels (~=0.13.2)
Requires-Dist: click (~=8.0.3)
Requires-Dist: setuptools (~=66.0.0)
Requires-Dist: biopython (~=1.79)
Requires-Dist: click-option-group
